ni/datamonikers/v1/client/__init__.py
ni/datamonikers/v1/client/_client.py
ni/datamonikers/v1/client/py.typed
ni_datamonikers_v1_client-1.0.0.dist-info/METADATA
ni_datamonikers_v1_client-1.0.0.dist-info/WHEEL
ni_datamonikers_v1_client-1.0.0.dist-info/RECORD
