Metadata-Version: 2.3
Name: ni.datamonikers.v1.client
Version: 1.0.0
Summary: gRPC Client for NI Data Moniker Service
License: MIT
Keywords: data-moniker,client
Author: NI
Author-email: opensource@ni.com
Maintainer: Joe Friedrichsen
Maintainer-email: joe.friedrichsen@emerson.com
Requires-Python: >=3.10,<4.0
Classifier: Development Status :: 5 - Production/Stable
Classifier: Intended Audience :: Developers
Classifier: Intended Audience :: Manufacturing
Classifier: Intended Audience :: Science/Research
Classifier: License :: OSI Approved :: MIT License
Classifier: Operating System :: Microsoft :: Windows
Classifier: Programming Language :: Python :: 3
Classifier: Programming Language :: Python :: 3.10
Classifier: Programming Language :: Python :: 3.11
Classifier: Programming Language :: Python :: 3.12
Classifier: Programming Language :: Python :: 3.13
Classifier: Programming Language :: Python :: 3.14
Classifier: Programming Language :: Python :: Implementation :: CPython
Requires-Dist: ni-datamonikers-v1-proto (>=1.0.0)
Requires-Dist: ni-grpc-extensions (>=1.1.0)
Project-URL: Documentation, https://nidatamonikersv1client.readthedocs.io/en/latest/
Project-URL: Repository, https://github.com/ni/ni-apis-python
